<mujoco model="Trilinear flex sphere lr sweep">
  <compiler meshdir="." autolimits="true"/>
  <include file="/home/mshashank02/SoftObjectsV2/objects/large_1/tet_coarse/scene.xml"/>

  <option solver="CG" tolerance="1e-6" timestep="1e-3" integrator="implicitfast"/>
  <size memory="512M"/>

  <visual>
    <map stiffness="100"/>
    <rgba bv="0 0 0 0" bvactive="0 0 0 0"/>
  </visual>

  <worldbody>
    <geom type="box" pos="1.5 0 0.25" size=".5 3 .25"/>
    <geom type="box" pos="0 0 0.25" size="3 3 .05" euler="0 15 0"/>

    <flexcomp name="soft_lr_0p02" type="gmsh"
              file="/home/mshashank02/SoftObjectsV2/objects_sphere/sphere_macro_high_rough_high_sweep/sphere_macro_high_rough_high_lr_0p02.msh"
              dim="3" dof="trilinear"
              pos="-1.2 -0.8 1.2" scale="0.1 0.1 0.1" mass="10" radius="0.001">
      <elasticity young="1e4" poisson="0.40" damping="0.12"/>
      <contact selfcollide="none" internal="false"/>
    </flexcomp>
    <body name="rigid_lr_0p02" pos="-1.2 -0.4 1.2">
      <freejoint/>
      <inertial pos="0 0 0" mass="0.5" diaginertia="1e-3 1e-3 1e-3"/>
      <flexcomp name="rigid_copy_lr_0p02" type="gmsh"
                file="/home/mshashank02/SoftObjectsV2/objects_sphere/sphere_macro_high_rough_high_sweep/sphere_macro_high_rough_high_lr_0p02.msh"
                dim="3" dof="trilinear" rigid="true"
                pos="0 0 0" scale="0.1 0.1 0.1" radius="0.001">
        <contact selfcollide="none" internal="false"/>
      </flexcomp>
    </body>

    <flexcomp name="soft_lr_0p04" type="gmsh"
              file="/home/mshashank02/SoftObjectsV2/objects_sphere/sphere_macro_high_rough_high_sweep/sphere_macro_high_rough_high_lr_0p04.msh"
              dim="3" dof="trilinear"
              pos="0.0 -0.8 1.2" scale="0.1 0.1 0.1" mass="10" radius="0.001">
      <elasticity young="1e4" poisson="0.40" damping="0.12"/>
      <contact selfcollide="none" internal="false"/>
    </flexcomp>
    <body name="rigid_lr_0p04" pos="0.0 -0.4 1.2">
      <freejoint/>
      <inertial pos="0 0 0" mass="0.5" diaginertia="1e-3 1e-3 1e-3"/>
      <flexcomp name="rigid_copy_lr_0p04" type="gmsh"
                file="/home/mshashank02/SoftObjectsV2/objects_sphere/sphere_macro_high_rough_high_sweep/sphere_macro_high_rough_high_lr_0p04.msh"
                dim="3" dof="trilinear" rigid="true"
                pos="0 0 0" scale="0.1 0.1 0.1" radius="0.001">
        <contact selfcollide="none" internal="false"/>
      </flexcomp>
    </body>

    <flexcomp name="soft_lr_0p06" type="gmsh"
              file="/home/mshashank02/SoftObjectsV2/objects_sphere/sphere_macro_high_rough_high_sweep/sphere_macro_high_rough_high_lr_0p06.msh"
              dim="3" dof="trilinear"
              pos="1.2 -0.8 1.2" scale="0.1 0.1 0.1" mass="10" radius="0.001">
      <elasticity young="1e4" poisson="0.40" damping="0.12"/>
      <contact selfcollide="none" internal="false"/>
    </flexcomp>
    <body name="rigid_lr_0p06" pos="1.2 -0.4 1.2">
      <freejoint/>
      <inertial pos="0 0 0" mass="0.5" diaginertia="1e-3 1e-3 1e-3"/>
      <flexcomp name="rigid_copy_lr_0p06" type="gmsh"
                file="/home/mshashank02/SoftObjectsV2/objects_sphere/sphere_macro_high_rough_high_sweep/sphere_macro_high_rough_high_lr_0p06.msh"
                dim="3" dof="trilinear" rigid="true"
                pos="0 0 0" scale="0.1 0.1 0.1" radius="0.001">
        <contact selfcollide="none" internal="false"/>
      </flexcomp>
    </body>

    <flexcomp name="soft_lr_0p08" type="gmsh"
              file="/home/mshashank02/SoftObjectsV2/objects_sphere/sphere_macro_high_rough_high_sweep/sphere_macro_high_rough_high_lr_0p08.msh"
              dim="3" dof="trilinear"
              pos="-1.2 0.8 1.2" scale="0.1 0.1 0.1" mass="10" radius="0.001">
      <elasticity young="1e4" poisson="0.40" damping="0.12"/>
      <contact selfcollide="none" internal="false"/>
    </flexcomp>
    <body name="rigid_lr_0p08" pos="-1.2 1.2 1.2">
      <freejoint/>
      <inertial pos="0 0 0" mass="0.5" diaginertia="1e-3 1e-3 1e-3"/>
      <flexcomp name="rigid_copy_lr_0p08" type="gmsh"
                file="/home/mshashank02/SoftObjectsV2/objects_sphere/sphere_macro_high_rough_high_sweep/sphere_macro_high_rough_high_lr_0p08.msh"
                dim="3" dof="trilinear" rigid="true"
                pos="0 0 0" scale="0.1 0.1 0.1" radius="0.001">
        <contact selfcollide="none" internal="false"/>
      </flexcomp>
    </body>

    <flexcomp name="soft_lr_0p10" type="gmsh"
              file="/home/mshashank02/SoftObjectsV2/objects_sphere/sphere_macro_high_rough_high_sweep/sphere_macro_high_rough_high_lr_0p10.msh"
              dim="3" dof="trilinear"
              pos="0.0 0.8 1.2" scale="0.1 0.1 0.1" mass="10" radius="0.001">
      <elasticity young="1e4" poisson="0.40" damping="0.12"/>
      <contact selfcollide="none" internal="false"/>
    </flexcomp>
    <body name="rigid_lr_0p10" pos="0.0 1.2 1.2">
      <freejoint/>
      <inertial pos="0 0 0" mass="0.5" diaginertia="1e-3 1e-3 1e-3"/>
      <flexcomp name="rigid_copy_lr_0p10" type="gmsh"
                file="/home/mshashank02/SoftObjectsV2/objects_sphere/sphere_macro_high_rough_high_sweep/sphere_macro_high_rough_high_lr_0p10.msh"
                dim="3" dof="trilinear" rigid="true"
                pos="0 0 0" scale="0.1 0.1 0.1" radius="0.001">
        <contact selfcollide="none" internal="false"/>
      </flexcomp>
    </body>

    <flexcomp name="soft_lr_0p12" type="gmsh"
              file="/home/mshashank02/SoftObjectsV2/objects_sphere/sphere_macro_high_rough_high_sweep/sphere_macro_high_rough_high_lr_0p12.msh"
              dim="3" dof="trilinear"
              pos="1.2 0.8 1.2" scale="0.1 0.1 0.1" mass="10" radius="0.001">
      <elasticity young="1e4" poisson="0.40" damping="0.12"/>
      <contact selfcollide="none" internal="false"/>
    </flexcomp>
    <body name="rigid_lr_0p12" pos="1.2 1.2 1.2">
      <freejoint/>
      <inertial pos="0 0 0" mass="0.5" diaginertia="1e-3 1e-3 1e-3"/>
      <flexcomp name="rigid_copy_lr_0p12" type="gmsh"
                file="/home/mshashank02/SoftObjectsV2/objects_sphere/sphere_macro_high_rough_high_sweep/sphere_macro_high_rough_high_lr_0p12.msh"
                dim="3" dof="trilinear" rigid="true"
                pos="0 0 0" scale="0.1 0.1 0.1" radius="0.001">
        <contact selfcollide="none" internal="false"/>
      </flexcomp>
    </body>
  </worldbody>
</mujoco>
